franklin_cli/__init__.py
franklin_cli/auth.py
franklin_cli/chrome.py
franklin_cli/config.py
franklin_cli/crash.py
franklin_cli/cutie.py
franklin_cli/desktop.py
franklin_cli/docker.py
franklin_cli/example_usage.py
franklin_cli/gitlab.py
franklin_cli/interfaces.py
franklin_cli/jupyter.py
franklin_cli/logger.py
franklin_cli/options.py
franklin_cli/pixi_deps.py
franklin_cli/plugin_interface.py
franklin_cli/system.py
franklin_cli/terminal.py
franklin_cli/update.py
franklin_cli/utils.py
franklin_cli/backends/__init__.py
franklin_cli/backends/adapter.py
franklin_cli/backends/base.py
franklin_cli/backends/cli_wrapper.py
franklin_cli/backends/config.py
franklin_cli/backends/examples.py
franklin_cli/backends/factory.py
franklin_cli/backends/github_backend.py
franklin_cli/backends/gitlab_backend.py
franklin_cli/backends/migration.py
franklin_cli/data/templates/exercise/.gitlab-ci.yml
franklin_cli/data/templates/exercise/.pixi.py
franklin_cli/data/templates/exercise/.test-notebook.sh
franklin_cli/data/templates/exercise/Dockerfile
franklin_cli/data/templates/exercise/README.md
franklin_cli/data/templates/exercise/exercise.ipynb
franklin_cli/data/templates/exercise/magic.py
franklin_cli/data/templates/exercise/pixi.toml
franklin_cli/data/templates/exercise/.devcontainer/devcontainer.json
franklin_cli/data/templates/exercise/.vscode/settings.json
franklin_cli/dependencies/__init__.py
franklin_cli/dependencies/dependency_checker.py
franklin_cli/dependencies/setup_py.py
franklin_cli-0.25.149.dist-info/licenses/LICENSE
franklin_cli-0.25.149.dist-info/METADATA
franklin_cli-0.25.149.dist-info/WHEEL
franklin_cli-0.25.149.dist-info/entry_points.txt
franklin_cli-0.25.149.dist-info/top_level.txt
franklin_cli-0.25.149.dist-info/RECORD
