Metadata-Version: 2.4
Name: franklin-cli
Version: 0.25.149
Summary: Terminal client for Jupyter exercises
Author-email: Kasper Munch <kaspermunch@birc.au.dk>
Maintainer-email: Kasper Munch <kaspermunch@birc.au.dk>
Project-URL: Homepage, https://munch-group.org/franklin
Project-URL: Documentation, https://munch-group.org/franklin
Project-URL: Repository, https://github.com/munch-group/franklin.git
Project-URL: Issues, https://github.com/munch-group/franklin_cli/issues
Keywords: teaching,data,jupyter,docker,git
Classifier: Development Status :: 4 - Beta
Classifier: Intended Audience :: Education
Classifier: Topic :: Software Development :: Build Tools
Classifier: Programming Language :: Python :: 3
Classifier: Programming Language :: Python :: 3.9
Classifier: Programming Language :: Python :: 3.10
Classifier: Programming Language :: Python :: 3.11
Classifier: Programming Language :: Python :: 3.12
Classifier: Programming Language :: Python :: 3.13
Requires-Python: >=3.9
License-File: LICENSE
Requires-Dist: requests>=2.32.3
Requires-Dist: colorama>=0.4.6
Requires-Dist: readchar>=4.0.5
Requires-Dist: click
Requires-Dist: click-plugins
Requires-Dist: psutil
Requires-Dist: jupyter
Requires-Dist: packaging
Requires-Dist: pyyaml
Requires-Dist: pyperclip
Requires-Dist: selenium
Requires-Dist: webdriver-manager
Requires-Dist: rapidfuzz
Requires-Dist: pycryptodome
Dynamic: license-file
